{
	"backtraceGraph" : 
	{
		"commands" : 
		[
			"install",
			"qt_install",
			"qt_internal_add_tool"
		],
		"files" : 
		[
			"qtbase/cmake/QtInstallHelpers.cmake",
			"qtbase/cmake/QtToolHelpers.cmake",
			"qtdeclarative/tools/qmltyperegistrar/CMakeLists.txt"
		],
		"nodes" : 
		[
			{
				"file" : 2
			},
			{
				"command" : 2,
				"file" : 2,
				"line" : 9,
				"parent" : 0
			},
			{
				"command" : 1,
				"file" : 1,
				"line" : 219,
				"parent" : 1
			},
			{
				"command" : 0,
				"file" : 0,
				"line" : 21,
				"parent" : 2
			}
		]
	},
	"installers" : 
	[
		{
			"backtrace" : 3,
			"component" : "Unspecified",
			"destination" : "./libexec",
			"paths" : 
			[
				"qtbase/libexec/qmltyperegistrar"
			],
			"targetId" : "qmltyperegistrar::@b7d96742f61bda066508",
			"targetIndex" : 2725,
			"type" : "target"
		}
	],
	"paths" : 
	{
		"build" : "qtdeclarative/tools/qmltyperegistrar",
		"source" : "qtdeclarative/tools/qmltyperegistrar"
	}
}
