{
	"backtrace" : 2,
	"backtraceGraph" : 
	{
		"commands" : 
		[
			"add_custom_target",
			"qt_build_repo_begin"
		],
		"files" : 
		[
			"/Users/johanravnandersen/Desktop/Universitet/Software/Projects-skeleton/PhotoshopLite/build_Qt5/qtbase/lib/cmake/Qt6BuildInternals/Qt6BuildInternalsConfig.cmake",
			"qtdoc/CMakeLists.txt"
		],
		"nodes" : 
		[
			{
				"file" : 1
			},
			{
				"command" : 1,
				"file" : 1,
				"line" : 35,
				"parent" : 0
			},
			{
				"command" : 0,
				"file" : 0,
				"line" : 473,
				"parent" : 1
			}
		]
	},
	"id" : "qt_plugins_qtdoc::@3e3e19ca4bb0a1418a40",
	"name" : "qt_plugins_qtdoc",
	"paths" : 
	{
		"build" : "qtdoc",
		"source" : "qtdoc"
	},
	"sources" : [],
	"type" : "UTILITY"
}
